{"faq_lc3tools.md":"54b2c659","homework_hw1.md":"3b57c440","homework_hw2.md":"03af35ca","homework_hw3.md":"0ea45d05","homework_hw4.md":"81f5cdeb","homework_hw5.md":"4adf77b2","homework_hw6.md":"63509600","index.md":"036d285c","judge.md":"0a2a9e4a","labs_lab1.md":"440148ae","labs_lab2.md":"cb5b94f3","labs_lab3.md":"668c4867","labs_lab4.md":"f0b9b69a","labs_lab5.md":"6aab09be","labs_lab6.md":"5885ec5e","labs_lab7.md":"d3ae12d6","labs_lab8.md":"3a659b11","resource_cpp.md":"d2475466","resource_cs.md":"7222652e","resource_data.md":"5228b4be","resource_ics.md":"ffecbec3","resource_vscode.md":"48a1f3f8","score.md":"55cf8410"}
